FLife/__init__.py
FLife/spectralData.py
FLife/tools.py
FLife/freq_domain/__init__.py
FLife/freq_domain/alpha075.py
FLife/freq_domain/bands_method.py
FLife/freq_domain/dirlik.py
FLife/freq_domain/fu_cebon.py
FLife/freq_domain/gao_moan.py
FLife/freq_domain/huang_moan.py
FLife/freq_domain/jiao_moan.py
FLife/freq_domain/jun_park.py
FLife/freq_domain/lotsberg.py
FLife/freq_domain/low.py
FLife/freq_domain/low_2014.py
FLife/freq_domain/modified_fu_cebon.py
FLife/freq_domain/narrowband.py
FLife/freq_domain/ortiz_chen.py
FLife/freq_domain/park.py
FLife/freq_domain/sakai_okamura.py
FLife/freq_domain/single_moment.py
FLife/freq_domain/tovo_benasciutti.py
FLife/freq_domain/wirsching_light.py
FLife/freq_domain/zhao_baker.py
FLife/multiaxial/__init__.py
FLife/multiaxial/cplane.py
FLife/multiaxial/criteria.py
FLife/multiaxial/eq_stress.py
FLife/time_domain/__init__.py
FLife/time_domain/rainflow.py
FLife/visualize/__init__.py
FLife/visualize/visualize.py
flife-2.0.6.dist-info/METADATA
flife-2.0.6.dist-info/WHEEL
flife-2.0.6.dist-info/licenses/LICENSE
flife-2.0.6.dist-info/RECORD
