Metadata-Version: 2.4
Name: FLife
Version: 2.0.6
Summary: Vibration Fatigue by Spectral Methods.
Project-URL: homepage, https://github.com/ladisk/FLife
Project-URL: documentation, https://flife.readthedocs.io/en/latest/index.html
Project-URL: source, https://github.com/ladisk/FLife
Author-email: "Aleš Zorman, Jaša Šonc, Matjaž Mršnik, Janko Slavič" <janko.slavic@fs.uni-lj.si>
Maintainer-email: "Janko Slavič, Domen Gorjup" <janko.slavic@fs.uni-lj.si>
License-Expression: MIT
License-File: LICENSE
Keywords: fatigue,spectral methods,structural dynamics,vibration
Classifier: Development Status :: 5 - Production/Stable
Classifier: Intended Audience :: Developers
Classifier: License :: OSI Approved :: MIT License
Classifier: Programming Language :: Python :: 3.9
Classifier: Topic :: Scientific/Engineering
Requires-Python: >=3.9
Requires-Dist: fatpack
Requires-Dist: lvm-read
Requires-Dist: matplotlib
Requires-Dist: numpy
Requires-Dist: pyexsi
Requires-Dist: pylint
Requires-Dist: pytest
Requires-Dist: pyvista[all]
Requires-Dist: pyvistaqt
Requires-Dist: rainflow
Requires-Dist: scipy
Provides-Extra: dev
Requires-Dist: build; extra == 'dev'
Requires-Dist: pytest; extra == 'dev'
Requires-Dist: sphinx; extra == 'dev'
Requires-Dist: sphinx-copybutton; extra == 'dev'
Requires-Dist: sphinx-rtd-theme; extra == 'dev'
Requires-Dist: twine; extra == 'dev'
Requires-Dist: wheel; extra == 'dev'
